opvious/__init__.py
opvious/__main__.py
opvious/client/__init__.py
opvious/client/common.py
opvious/client/handlers.py
opvious/common.py
opvious/data/__init__.py
opvious/data/outcomes.py
opvious/data/outlines.py
opvious/data/queued_solves.py
opvious/data/solves.py
opvious/data/tensors.py
opvious/executors/__init__.py
opvious/executors/aiohttp.py
opvious/executors/common.py
opvious/executors/pyodide.py
opvious/executors/urllib.py
opvious/modeling/__init__.py
opvious/modeling/ast.py
opvious/modeling/definitions.py
opvious/modeling/fragments.py
opvious/modeling/identifiers.py
opvious/modeling/model.py
opvious/modeling/quantified.py
opvious/notebooks.py
opvious/py.typed
opvious/specifications/__init__.py
opvious/specifications/external.py
opvious/specifications/local.py
opvious/transformations.py
opvious-0.24.0.dist-info/METADATA
opvious-0.24.0.dist-info/WHEEL
opvious-0.24.0.dist-info/licenses/LICENSE
opvious-0.24.0.dist-info/RECORD
