Metadata-Version: 2.4
Name: opvious
Version: 0.24.0
Summary: Opvious Python SDK
License-File: LICENSE
Author: Opvious Engineering
Author-email: oss@opvious.io
Requires-Python: >=3.12,<4
Classifier: Programming Language :: Python :: 3
Classifier: Programming Language :: Python :: 3.12
Classifier: Programming Language :: Python :: 3.13
Classifier: Programming Language :: Python :: 3.14
Provides-Extra: aio
Provides-Extra: cli
Requires-Dist: aiohttp (>=3.8,<4.0) ; extra == "aio"
Requires-Dist: backoff (>=2.2,<3.0)
Requires-Dist: brotli (>=1.2.0,<2.0.0) ; extra == "aio"
Requires-Dist: docopt-ng (>=0.9,<0.10) ; extra == "cli"
Requires-Dist: humanize (>=4.4.0,<5.0.0)
Requires-Dist: importnb (>=2023.1.7,<2024.0.0)
Requires-Dist: lru-dict (>=1.3.0,<2.0.0) ; extra == "aio"
Requires-Dist: numpy (>=2.3)
Requires-Dist: pandas (>=2.2)
Project-URL: Repository, https://github.com/opvious/sdk.py
